fuzzycsv/__init__.py
fuzzycsv-0.0.1.dist-info/LICENSE
fuzzycsv-0.0.1.dist-info/METADATA
fuzzycsv-0.0.1.dist-info/WHEEL
fuzzycsv-0.0.1.dist-info/top_level.txt
fuzzycsv-0.0.1.dist-info/RECORD
